{
    "format_version": "1.12",
    "minecraft:recipe_shapeless": {
        "description": {
            "identifier": "minecraft:stonecutter_spruce_wood"
        },
        "tags": [
            "stonecutter"
        ],
        "priority": 1,
        "ingredients": [
            {
                "item": "minecraft:spruce_log",
                "data": 0
            }
        ],
        "result": {
            "item": "minecraft:spruce_wood",
            "data": 0,
            "count": 1
        }
    }
}